manylocales/__about__.py
manylocales/__init__.py
manylocales/cli.py
manylocales/constants.py
manylocales-0.1.0.dist-info/METADATA
manylocales-0.1.0.dist-info/WHEEL
manylocales-0.1.0.dist-info/entry_points.txt
manylocales-0.1.0.dist-info/licenses/LICENSE.md
manylocales-0.1.0.dist-info/RECORD
